wek.py
wek-0.1.0.dist-info/LICENSE.txt
wek-0.1.0.dist-info/METADATA
wek-0.1.0.dist-info/WHEEL
wek-0.1.0.dist-info/entry_points.txt
wek-0.1.0.dist-info/top_level.txt
wek-0.1.0.dist-info/RECORD
