Metadata-Version: 2.1
Name: wek
Version: 0.1.0
Summary: Keep your windows machine awake.
Home-page: https://github.com/kmaork/wek
Author: Maor Kleinberger
Author-email: kmaork@gmail.com
License: UNKNOWN
Keywords: windows sleep awake
Platform: UNKNOWN
